{"components_maz-accordion.md":"BKuIFDlP","components_maz-bottom-sheet.md":"Q1fJ3-H3","guide_colors.md":"DBsjb1Jd","components_maz-checkbox.md":"DtIeNIPW","guide_dark-mode.md":"BDcgq3cj","components_maz-transition-expand.md":"uOVeCLHY","index.md":"BGjICNQg","helpers_capitalize.md":"7Pealu5I","components_maz-badge.md":"CGRpfFZP","helpers_currency.md":"C9EdFItJ","made-with-maz-ui.md":"UJKveDCe","helpers_date.md":"fvhT4gvC","helpers_number.md":"B4oK1JBb","guide_nuxt.md":"wnxCQiYw","components_maz-link.md":"CvxFi3W7","components_maz-picker.md":"z8AtlsW5","components_maz-btn.md":"BSLPBnOv","components_maz-stepper.md":"yg40qDK8","components_maz-tabs.md":"ClzWzXQ4","components_maz-reading-progress-bar.md":"CRciVBLn","components_maz-select.md":"C36-YSgu","components_maz-slider.md":"BUSw9Gna","components_maz-spinner.md":"DFFxRB5Y","components_maz-dialog-promise.md":"hFIgmiAp","composables_use-theme-handler.md":"67edx0KQ","components_maz-pagination.md":"BgmGSBgQ","components_maz-dialog.md":"cZBX1UP1","helpers_country-code-to-unicode-flag.md":"CjhqXXtC","components_maz-radio.md":"Er26I0O-","plugins_toaster.md":"ClPsJ9pE","components_maz-card.md":"BiJjxPKu","components_maz-carousel.md":"D3tPneRI","guide_theme.md":"WwVlvyt_","components_maz-avatar.md":"B1noF8U4","components_maz-radio-buttons.md":"DMPwgGAZ","components_maz-drawer.md":"Bqhh2npa","components_maz-gallery.md":"CkvMIVw7","components_maz-icon.md":"BDkBbWVH","components_maz-input-price.md":"Buc6omzs","components_maz-input-tags.md":"Bo_uPwOC","components_maz-backdrop.md":"DVSCinqW","components_maz-lazy-img.md":"DuAMjB73","composables_use-toast.md":"C-Bv3xyB","composables_use-timer.md":"CMk40n9w","composables_use-user-visibility.md":"Dl8B2ZK8","composables_use-wait.md":"DNdPo91S","components_maz-loading-bar.md":"BN04Wavi","composables_use-window-size.md":"BN6xf-HL","directives_click-outside.md":"BvObT5bQ","directives_fullscreen-img.md":"BLG3ainu","directives_zoom-img.md":"DgGY_Sl1","components_maz-dropdown.md":"BaQWvt-Y","guide_cli.md":"CNsdqcX_","directives_lazy-img.md":"CJJSCsc1","components_maz-switch.md":"DqrF-Jex","components_maz-input.md":"D-lYqqcB","components_maz-textarea.md":"B-kSqgPa","components_maz-pull-to-refresh.md":"C0WwJqV1","composables_use-aos.md":"9rvj4pmC","components_maz-table.md":"Cs4aPBg8","components_maz-input-code.md":"C--CIEEH","plugins_wait.md":"TS_Ru9Ug","plugins_aos.md":"Bwe74Ey9","composables_use-idle-timeout.md":"Dx_QC-8R","components_maz-input-number.md":"C87wvnlI","components_maz-fullscreen-loader.md":"D6S5rAqm","composables_use-string-matching.md":"Bs3lCKzf","composables_use-reading-time.md":"DJcBzrW1","composables_use-swipe.md":"DPO-Xy18","composables_use-breakpoints.md":"BhPSgBc5","components_maz-dropzone.md":"DFRMvB9S","directives_closable.md":"COBE4kXD","components_maz-card-spotlight.md":"DmdXNVdr","components_maz-phone-number-input.md":"sn_6SHjQ","guide_getting-started.md":"BfvwJO-T","components_maz-chart.md":"Bm1MEaz1"}
