{"components_maz-drawer.md":"xszr0OXp","components_maz-checkbox.md":"Siqoqkuw","components_maz-accordion.md":"JmmzPKur","components_maz-input-number.md":"7CCFL1pY","components_maz-input-price.md":"-EdeUYd7","components_maz-input-tags.md":"r9iqLxP8","components_maz-loading-bar.md":"yFcxA4pv","components_maz-gallery.md":"2iCJ4foJ","components_maz-dropdown.md":"mIQ9Zcld","components_maz-input-code.md":"06rS_4hd","components_maz-carousel.md":"WjD-NPVY","components_maz-btn.md":"XJVEPylp","components_maz-avatar.md":"_XW9b-vL","components_maz-bottom-sheet.md":"3TlPXFQo","components_maz-dialog.md":"P69oXfDM","components_maz-dropzone.md":"BDYNt2Yq","components_maz-lazy-img.md":"wb1AVkAA","components_maz-fullscreen-loader.md":"dDGRRxLc","components_maz-badge.md":"YpsCZRLi","guide_colors.md":"4fG9mvlS","components_maz-spinner.md":"u1ANZK2Q","components_maz-switch.md":"WVOv_hjK","composables_use-theme-handler.md":"Wp_yRIov","components_maz-icon.md":"OyCVf7iU","composables_use-timer.md":"5izaRHKX","components_maz-radio.md":"yUk_T9qY","guide_theme.md":"rzUupUB1","helpers_capitalize.md":"1omFxDe7","helpers_country-code-to-unicode-flag.md":"yY8HKIeI","composables_use-toast.md":"dnLSULeF","components_maz-select.md":"d_ZhnUzi","components_maz-backdrop.md":"49Fxb_iG","directives_click-outside.md":"Z4iHxj2n","directives_fullscreen-img.md":"eb_aoxDy","components_maz-radio-buttons.md":"LWcUBJ1W","components_maz-picker.md":"lb0ObcJS","guide_cli.md":"aXZ-RBQb","directives_zoom-img.md":"IoEbdk-e","components_maz-input.md":"kVaKraio","composables_use-user-visibility.md":"bBWsovmf","guide_dark-mode.md":"Skt4Ep4-","guide_getting-started.md":"m8sBEVOm","composables_use-window-size.md":"zgI1jquJ","components_maz-phone-number-input.md":"VnoT_-UC","guide_nuxt.md":"FQuBAcc0","components_maz-slider.md":"h8LtWyKx","composables_use-wait.md":"PdDNMS2x","components_maz-tabs.md":"NrNJ_vh8","components_maz-card.md":"okEWmzye","components_maz-table.md":"4IP5mR_2","helpers_number.md":"IVlCHMLt","made-with-maz-ui.md":"CJa17i9z","plugins_aos.md":"HNz3KcIH","components_maz-pull-to-refresh.md":"YM3eFPY1","plugins_wait.md":"PkqWRR7V","plugins_toaster.md":"hAc4rJ76","helpers_date.md":"1GVwVU07","components_maz-textarea.md":"A0cL-T-F","components_maz-transition-expand.md":"npqU1TAx","composables_use-aos.md":"JZED4eBd","composables_use-breakpoints.md":"GnmEUgww","composables_use-swipe.md":"_0CYAxks","directives_lazy-img.md":"chEbujDK","components_maz-card-spotlight.md":"gQM7Qbdc","composables_use-idle-timeout.md":"1_l0ukgT","components_maz-chart.md":"JLx9u3CP","index.md":"TWNHvs7Q","components_maz-dialog-promise.md":"QZ_jliYA","helpers_currency.md":"AQ7AHsKn","components_maz-stepper.md":"_AM58rdE"}
