{"components_maz-card-spotlight.md":"D-GLqeOc","components_maz-fullscreen-loader.md":"tOULu-ys","components_maz-checkbox.md":"_yviOMDl","helpers_currency.md":"N01GOGHI","helpers_date.md":"DGP_hh-B","helpers_number.md":"B_TmQCta","index.md":"Bl17huaK","made-with-maz-ui.md":"BT5tac18","plugins_toaster.md":"C1Mx6K0E","components_maz-chart.md":"BwNfx5oq","components_maz-gallery.md":"B3ic1rR7","components_maz-bottom-sheet.md":"CA5uNuJb","components_maz-avatar.md":"Bmw4jDKd","components_maz-badge.md":"DJf0LaVZ","components_maz-input-number.md":"Canydrrk","components_maz-input-tags.md":"BsgsFMNH","components_maz-input.md":"YE2ajZva","components_maz-lazy-img.md":"DYANOa27","components_maz-input-price.md":"Bpe_mIAx","components_maz-pagination.md":"DnUUhFjN","components_maz-loading-bar.md":"BRXAlP0F","components_maz-input-code.md":"C3efwlEQ","components_maz-dialog-promise.md":"ucFtcCln","components_maz-pull-to-refresh.md":"CcK2pRpN","components_maz-slider.md":"Dm6LiIEz","components_maz-textarea.md":"CWvbxgWm","guide_cli.md":"CXlnSoAN","components_maz-btn.md":"CqExexph","directives_click-outside.md":"C99jGwny","composables_use-window-size.md":"DvZaP75L","components_maz-radio.md":"ZvxAXSrt","composables_use-wait.md":"C1-bkmWk","components_maz-stepper.md":"B5QdJzt3","composables_use-user-visibility.md":"BHmN1INa","guide_getting-started.md":"mRfMoQ7Y","composables_use-aos.md":"CGm_nO4P","components_maz-transition-expand.md":"ccQ2uSYP","components_maz-select.md":"DQQWhslt","components_maz-reading-progress-bar.md":"BUP0kGi4","plugins_wait.md":"C8lFa2Th","components_maz-spinner.md":"BbpB62Rw","directives_zoom-img.md":"Dt_8j3Sd","guide_dark-mode.md":"BANImfi0","composables_use-breakpoints.md":"DYhJqNrf","components_maz-card.md":"H2Vk0dH1","components_maz-carousel.md":"BmHrtXHh","plugins_aos.md":"DBVfAiE4","components_maz-radio-buttons.md":"CL5uRJI6","helpers_capitalize.md":"x9NPPLgr","components_maz-switch.md":"PJ1yLvER","directives_fullscreen-img.md":"Cw6QTqY6","guide_nuxt.md":"CYL6qDjM","components_maz-tabs.md":"Da5usrib","composables_use-toast.md":"DfPsrq1I","components_maz-icon.md":"BEpTGj-F","guide_colors.md":"--KBwT2R","composables_use-theme-handler.md":"BY-ZjzG6","components_maz-table.md":"DiVU64mw","helpers_country-code-to-unicode-flag.md":"DU0LD-O-","composables_use-timer.md":"QpKyyCpO","components_maz-accordion.md":"D3__ovEC","components_maz-dropzone.md":"DmshhznC","composables_use-swipe.md":"BkTNL0co","composables_use-reading-time.md":"BQFM-Qx4","components_maz-dialog.md":"3b-kzgAG","components_maz-phone-number-input.md":"B0-XP0F_","components_maz-backdrop.md":"CzfUIXYy","guide_theme.md":"sB9AIL4r","composables_use-idle-timeout.md":"DKqi6kf4","components_maz-picker.md":"CuZsR08-","components_maz-dropdown.md":"CkTUXeOu","components_maz-drawer.md":"CMNhCa9U","directives_lazy-img.md":"DaFZUq92"}
